{
	"message": "Tải danh sách âm nhạc thành công",
	"success": true,
	"data": [
		{
			"_id": "683e90a097c251aaa8d2fc4b",
			"name_music": "test",
			"category": "trending",
			"time_format": "4:16",
			"name_singer": "trending",
			"type": "trending",
			"src_music": "https://firebasestorage.googleapis.com/v0/b/aloimp3.appspot.com/o/mp3%2FB%E1%BA%A0C%20PH%E1%BA%ACN%20%EF%BD%9C%20ICM%20x%20JACK%20%EF%BD%9C%20OFFICIAL%20MV.mp3?alt=media&token=d6156583-dd63-4e90-b307-2c74d84354af",
			"image_music": "https://firebasestorage.googleapis.com/v0/b/aloimp3.appspot.com/o/images%2Fdownload.webp?alt=media&token=ac689153-d0ed-4f3d-b183-4ab81b4f4659",
			"createdAt": "1970-01-21T05:48:50.720Z",
			"updatedAt": "1970-01-21T05:48:50.720Z",
			"__v": 0
		},
		{
			"_id": "683e90402e12779917473ae4",
			"name_music": "TEST",
			"category": "trending",
			"time_format": "4:16",
			"name_singer": "TEST",
			"type": "trending",
			"src_music": "https://firebasestorage.googleapis.com/v0/b/aloimp3.appspot.com/o/mp3%2FB%E1%BA%A0C%20PH%E1%BA%ACN%20%EF%BD%9C%20ICM%20x%20JACK%20%EF%BD%9C%20OFFICIAL%20MV.mp3?alt=media&token=71fa072e-e5f7-46ee-babc-8d337148530f",
			"image_music": "https://firebasestorage.googleapis.com/v0/b/aloimp3.appspot.com/o/images%2Fdownload.webp?alt=media&token=e630ac53-a30b-40b3-9b24-0939b4652a2e",
			"createdAt": "1970-01-21T05:48:50.624Z",
			"updatedAt": "1970-01-21T05:48:50.624Z",
			"__v": 0
		},
		{
			"_id": "683e8fd52e12779917473adb",
			"name_music": "J97",
			"category": "trending",
			"time_format": "4:16",
			"name_singer": "J97",
			"type": "trending",
			"src_music": "https://firebasestorage.googleapis.com/v0/b/aloimp3.appspot.com/o/mp3%2FB%E1%BA%A0C%20PH%E1%BA%ACN%20%EF%BD%9C%20ICM%20x%20JACK%20%EF%BD%9C%20OFFICIAL%20MV.mp3?alt=media&token=3ab8ac3f-a0fb-4d98-b516-0b31973400c6",
			"image_music": "https://firebasestorage.googleapis.com/v0/b/aloimp3.appspot.com/o/images%2Fdownload.webp?alt=media&token=e35290a1-cc7d-4717-98ad-278563946796",
			"createdAt": "1970-01-21T05:48:50.517Z",
			"updatedAt": "1970-01-21T05:48:50.517Z",
			"__v": 0
		},
		{
			"_id": "6599559af22adde54a42e77e",
			"name_music": "CALL OF SILENT x AKUMA NA KO x AOT",
			"category": "trending",
			"time_format": "3:06",
			"name_singer": "MIT ft JAPANDEE",
			"type": "trending",
			"src_music": "https://firebasestorage.googleapis.com/v0/b/aloimp3.appspot.com/o/mp3%2FCALL%20OF%20SILENT%20x%20AKUMA%20NA%20KO%20x%20AOT%20__%20MIT%20ft%20JAPANDEE%20__%20B%E1%BA%A3n%20Ph%E1%BB%91i%20from_T-Libra%20%E2%99%8E%E2%9C%A8.mp3?alt=media&token=94c5202f-a551-46bc-b1f4-927f653542de",
			"image_music": "https://firebasestorage.googleapis.com/v0/b/aloimp3.appspot.com/o/images%2Fab67616d00001e02b26afb279fe77155fb32a998%20(1).jpeg?alt=media&token=2660dbdb-21ec-4db2-b254-b65b7b38130c",
			"createdAt": "1970-01-20T17:29:07.738Z",
			"updatedAt": "1970-01-20T17:29:07.738Z",
			"__v": 0
		},
		{
			"_id": "64edf4fb500b4a53acae3498",
			"name_music": "Hero",
			"category": "edm",
			"time_format": "3:18",
			"name_singer": "Cash Cash ft Christina Perri",
			"type": "trending",
			"src_music": "https://firebasestorage.googleapis.com/v0/b/aloimp3.appspot.com/o/mp3%2Fy2mate.com%20-%20Hero%E1%B4%B8%CA%B8%CA%B3%E1%B6%A6%E1%B6%9C%20%20Cash%20Cash%20ft%20Christina%20Perri%20%20TikTok%20132.mp3?alt=media&token=c78fb68d-af68-49a0-a7d6-409e7a825739",
			"image_music": "https://firebasestorage.googleapis.com/v0/b/aloimp3.appspot.com/o/images%2F117.jpeg?alt=media&token=0b02eb16-d3c5-4ef8-ad15-8c678c51c0cc",
			"createdAt": "1970-01-20T14:21:56.347Z",
			"updatedAt": "1970-01-20T14:21:56.347Z",
			"__v": 0
		},
		{
			"_id": "64edf2f170de0ce47b114d32",
			"name_music": "Centuries",
			"category": "edm",
			"time_format": "4:21",
			"name_singer": " Fall Out Boy,  LEXIM Remix",
			"type": "trending",
			"src_music": "https://firebasestorage.googleapis.com/v0/b/aloimp3.appspot.com/o/mp3%2Fy2mate.com%20-%20Fall%20Out%20Boy%20%20Centuries%20LEXIM%20Remix.mp3?alt=media&token=51f435df-a663-4246-9dc0-be0039be5f6c",
			"image_music": "https://firebasestorage.googleapis.com/v0/b/aloimp3.appspot.com/o/images%2F114.jpeg?alt=media&token=d8ecc82b-abb8-4839-ba53-533734fbf5b5",
			"createdAt": "1970-01-20T14:21:55.825Z",
			"updatedAt": "1970-01-20T14:21:55.825Z",
			"__v": 0
		},
		{
			"_id": "64edf27770de0ce47b114d2f",
			"name_music": "Against the Sun",
			"category": "edm",
			"time_format": "3:32",
			"name_singer": "Anna Yvette Monstercat Release",
			"type": "trending",
			"src_music": "https://firebasestorage.googleapis.com/v0/b/aloimp3.appspot.com/o/mp3%2Fy2mate.com%20-%20Drumstep%20%20Rootkit%20%20Against%20the%20Sun%20feat%20Anna%20Yvette%20Monstercat%20Release.mp3?alt=media&token=5d0e2f25-47dc-43bf-a85e-f604dc77e8cc",
			"image_music": "https://firebasestorage.googleapis.com/v0/b/aloimp3.appspot.com/o/images%2F113.jpeg?alt=media&token=6d956ca0-47c2-4e34-aec7-6c2e02f25418",
			"createdAt": "1970-01-20T14:21:55.703Z",
			"updatedAt": "1970-01-20T14:21:55.703Z",
			"__v": 0
		},
		{
			"_id": "64edf16770de0ce47b114d27",
			"name_music": "Umbrella",
			"category": "chill",
			"time_format": "4:45",
			"name_singer": "Ember Island, Matte Remix  Electronic",
			"type": "trending",
			"src_music": "https://firebasestorage.googleapis.com/v0/b/aloimp3.appspot.com/o/mp3%2Fy2mate.com%20-%20Ember%20Island%20%20Umbrella%20Matte%20Remix%20%20Electronic.mp3?alt=media&token=9f95924f-7537-4f6a-b310-f202882e6dce",
			"image_music": "https://firebasestorage.googleapis.com/v0/b/aloimp3.appspot.com/o/images%2F112.jpeg?alt=media&token=7b054d66-8bca-4c35-8b19-b1266f92e804",
			"createdAt": "1970-01-20T14:21:55.431Z",
			"updatedAt": "1970-01-20T14:21:55.431Z",
			"__v": 0
		},
		{
			"_id": "64edef78500b4a53acae3459",
			"name_music": "Flowers ",
			"category": "edm",
			"time_format": "3:19",
			"name_singer": "Dirty Palm, Conor Ross, Chandler Blase",
			"type": "trending",
			"src_music": "https://firebasestorage.googleapis.com/v0/b/aloimp3.appspot.com/o/mp3%2Fy2mate.com%20-%20Dirty%20Palm%20%20Conor%20Ross%20%20Chandler%20Blas%C3%A9%E1%B4%B8%CA%B8%CA%B3%E1%B6%A6%E1%B6%9CFlowers%20%20Top%20Hot%20Tik%20Tok%20%20044.mp3?alt=media&token=cd77c644-4779-487f-b094-0bdfc382b1a8",
			"image_music": "https://firebasestorage.googleapis.com/v0/b/aloimp3.appspot.com/o/images%2F109.jpeg?alt=media&token=6974a184-6278-4be8-9bf3-e71fcf4a7636",
			"createdAt": "1970-01-20T14:21:54.936Z",
			"updatedAt": "1970-01-20T14:21:54.936Z",
			"__v": 0
		},
		{
			"_id": "64eded02881f01bc7eeffa88",
			"name_music": "Death Bed",
			"category": "chill",
			"time_format": "2:51",
			"name_singer": "Besomorph Anthony Keyrouz ft Lunis",
			"type": "trending",
			"src_music": "https://firebasestorage.googleapis.com/v0/b/aloimp3.appspot.com/o/mp3%2Fy2mate.com%20-%20Death%20Bed%20%20Besomorph%20%20Anthony%20Keyrouz%20ft%20LunisLyrics%20%20Vietsub.mp3?alt=media&token=28d20795-3dfa-45e7-8222-faa8d0cf6682",
			"image_music": "https://firebasestorage.googleapis.com/v0/b/aloimp3.appspot.com/o/images%2F106.jpeg?alt=media&token=899defc4-97a4-4e53-8d6c-75fdf9511698",
			"createdAt": "1970-01-20T14:21:54.306Z",
			"updatedAt": "1970-01-20T14:21:54.306Z",
			"__v": 0
		},
		{
			"_id": "64edec8f881f01bc7eeffa85",
			"name_music": "Come Back For You",
			"category": "chill",
			"time_format": "3:52",
			"name_singer": "Elephante ft Matluck",
			"type": "trending",
			"src_music": "https://firebasestorage.googleapis.com/v0/b/aloimp3.appspot.com/o/mp3%2Fy2mate.com%20-%20Come%20Back%20For%20You%20%20Elephante%20ft%20MatluckLyrics%20%20VietsubTikTok.mp3?alt=media&token=4f2558bd-e698-47bd-9c4b-498e9f9c293c",
			"image_music": "https://firebasestorage.googleapis.com/v0/b/aloimp3.appspot.com/o/images%2F105.jpeg?alt=media&token=ec844cf8-9a47-438e-bff7-20d5ce275b32",
			"createdAt": "1970-01-20T14:21:54.191Z",
			"updatedAt": "1970-01-20T14:21:54.191Z",
			"__v": 0
		},
		{
			"_id": "64ed8cc232bd02fa15344d3b",
			"name_music": "How To Love",
			"category": "chill",
			"time_format": "3:36",
			"name_singer": "Cash Cash  Sofia Reyes",
			"type": "trending",
			"src_music": "https://firebasestorage.googleapis.com/v0/b/aloimp3.appspot.com/o/mp3%2Fy2mate.com%20-%20Cash%20Cash%20%20Sofia%20Reyes%E1%B4%B8%CA%B8%CA%B3%E1%B6%A6%E1%B6%9CHow%20To%20Love%20%20Nh%E1%BA%A1c%20Tik%20Tok%20B%E1%BA%A5t%20H%E1%BB%A7%20%20001.mp3?alt=media&token=750c0d57-d3ad-4994-b7c5-305c16d4885e",
			"image_music": "https://firebasestorage.googleapis.com/v0/b/aloimp3.appspot.com/o/images%2F101.jpeg?alt=media&token=35e5c836-02a2-4362-a7ab-e625edd65ac2",
			"createdAt": "1970-01-20T14:21:29.666Z",
			"updatedAt": "1970-01-20T14:21:29.666Z",
			"__v": 0
		}
	]
}
